django_signals_conf/__init__.py
django_signals_conf/management/__init__.py
django_signals_conf/management/commands/__init__.py
django_signals_conf/management/commands/createsignals.py
django_signals_conf-0.1.1.dist-info/LICENSE
django_signals_conf-0.1.1.dist-info/METADATA
django_signals_conf-0.1.1.dist-info/WHEEL
django_signals_conf-0.1.1.dist-info/top_level.txt
django_signals_conf-0.1.1.dist-info/RECORD
