Metadata-Version: 2.1
Name: django-signals-conf
Version: 0.1.1
Summary: The library helps configure signals for django projects faster and easier
Home-page: https://github.com/tinhpb9x/django-signals-conf/
Author: Tinh Pham Ba
Author-email: tinhpb9x@gmail.com
License: MIT
Platform: UNKNOWN
Classifier: Programming Language :: Python :: 3
Classifier: License :: OSI Approved :: MIT License
Classifier: Operating System :: OS Independent
Requires-Python: >3.0
Requires-Dist: Django <5.0
